st3215/__init__.py
st3215/group_sync_read.py
st3215/group_sync_write.py
st3215/port_handler.py
st3215/protocol_packet_handler.py
st3215/st3215.py
st3215/values.py
st3215-0.4.0.dist-info/licenses/LICENSE
st3215-0.4.0.dist-info/METADATA
st3215-0.4.0.dist-info/WHEEL
st3215-0.4.0.dist-info/top_level.txt
st3215-0.4.0.dist-info/RECORD
